pyspeechanalysis/__init__.py
pyspeechanalysis/analysis.py
pyspeechanalysis-0.0.1.dist-info/LICENSE
pyspeechanalysis-0.0.1.dist-info/METADATA
pyspeechanalysis-0.0.1.dist-info/WHEEL
pyspeechanalysis-0.0.1.dist-info/top_level.txt
pyspeechanalysis-0.0.1.dist-info/RECORD
