Metadata-Version: 2.1
Name: pyspeechanalysis
Version: 0.0.1
Summary: Module for Speech Processing
Home-page: UNKNOWN
Author: Ittipon Bangudsareh
Author-email: edocstudio.info@gmail.com
License: MIT
Keywords: python,speech,signal,processing,speech processing,signal processing
Platform: UNKNOWN
Classifier: Development Status :: 5 - Production/Stable
Classifier: Intended Audience :: Developers
Classifier: Programming Language :: Python :: 3
Classifier: Operating System :: Unix
Classifier: Operating System :: MacOS :: MacOS X
Classifier: Operating System :: Microsoft :: Windows
Requires-Dist: numpy
Requires-Dist: matplotlib
